hello/__init__.py
hello/hello.py
my_latest_hello_world-0.0.6.dist-info/LICENSE
my_latest_hello_world-0.0.6.dist-info/METADATA
my_latest_hello_world-0.0.6.dist-info/WHEEL
my_latest_hello_world-0.0.6.dist-info/top_level.txt
my_latest_hello_world-0.0.6.dist-info/RECORD
